lottery_generator/__init__.py
lottery_generator/main.py
lottery_generator-1.1.0.dist-info/LICENSE
lottery_generator-1.1.0.dist-info/METADATA
lottery_generator-1.1.0.dist-info/WHEEL
lottery_generator-1.1.0.dist-info/entry_points.txt
lottery_generator-1.1.0.dist-info/top_level.txt
lottery_generator-1.1.0.dist-info/RECORD
