Metadata-Version: 2.1
Name: lottery-generator
Version: 1.1.0
Summary: very helpful lottery
Home-page: https://github.com/VadimTrubay/lottery_generator.git
Author: Trubay_Vadim
Author-email: vadnetvadnet@ukr.net
License: MIT
License-File: LICENSE
Requires-Dist: colorama
